wxmp_cli/__init__.py
wxmp_cli/__version__.py
wxmp_cli/core/__init__.py
wxmp_cli/core/base.py
wxmp_cli/core/commands/__init__.py
wxmp_cli/core/commands/login.py
wxmp_cli/core/commands/tag.py
wxmp_cli/core/commands/user.py
wxmp_cli/wx/__init__.py
wxmp_cli/wx/mp1421140183.py
wxmp_cli/wx/mp1421140837.py
wxmp_cli/wx/mp1421140839.py
wxmp_cli-0.1.0.dist-info/METADATA
wxmp_cli-0.1.0.dist-info/WHEEL
wxmp_cli-0.1.0.dist-info/entry_points.txt
wxmp_cli-0.1.0.dist-info/top_level.txt
wxmp_cli-0.1.0.dist-info/RECORD
